README.md
setup.py
Flask_MIME_Encoders.egg-info/PKG-INFO
Flask_MIME_Encoders.egg-info/SOURCES.txt
Flask_MIME_Encoders.egg-info/dependency_links.txt
Flask_MIME_Encoders.egg-info/namespace_packages.txt
Flask_MIME_Encoders.egg-info/requires.txt
Flask_MIME_Encoders.egg-info/top_level.txt
Flask_MIME_Encoders.egg-info/zip-safe
lib/__init__.py
lib/json.py
lib/json_iso8601.py