Metadata-Version: 1.1
Name: Flask-MIME-Encoders
Version: 0.1.2
Summary: Extensible Flask MIME encoders and decoders
Home-page: https://github.com/salsita/flask-mime-encoders
Author: Salsita Software
Author-email: python@salsitasoft.com
License: MIT
Download-URL: https://github.com/salsita/flask-mime-encoders/tarball/v0.1.2
Keywords: Flask,MIME,JSON,REST,API
Platform: any
Classifier: Development Status :: 4 - Beta
Classifier: Environment :: Web Environment
Classifier: Framework :: Flask
Classifier: Operating System :: OS Independent
Classifier: Intended Audience :: Developers
Classifier: Programming Language :: Python
Classifier: Programming Language :: Python :: 2.6
Classifier: Programming Language :: Python :: 2.7
Classifier: Programming Language :: Python :: 3.3
Classifier: Programming Language :: Python :: 3.4
Classifier: License :: OSI Approved :: MIT License
Classifier: Topic :: Internet :: WWW/HTTP
Classifier: Topic :: Internet :: WWW/HTTP :: Dynamic Content
Classifier: Topic :: Text Processing :: Markup
Classifier: Topic :: Software Development :: Libraries :: Python Modules
